keras/__init__.py
keras/_tf_keras/__init__.py
keras/_tf_keras/keras/__init__.py
keras/_tf_keras/keras/activations/__init__.py
keras/_tf_keras/keras/applications/__init__.py
keras/_tf_keras/keras/applications/convnext/__init__.py
keras/_tf_keras/keras/applications/densenet/__init__.py
keras/_tf_keras/keras/applications/efficientnet/__init__.py
keras/_tf_keras/keras/applications/efficientnet_v2/__init__.py
keras/_tf_keras/keras/applications/imagenet_utils/__init__.py
keras/_tf_keras/keras/applications/inception_resnet_v2/__init__.py
keras/_tf_keras/keras/applications/inception_v3/__init__.py
keras/_tf_keras/keras/applications/mobilenet/__init__.py
keras/_tf_keras/keras/applications/mobilenet_v2/__init__.py
keras/_tf_keras/keras/applications/mobilenet_v3/__init__.py
keras/_tf_keras/keras/applications/nasnet/__init__.py
keras/_tf_keras/keras/applications/resnet/__init__.py
keras/_tf_keras/keras/applications/resnet50/__init__.py
keras/_tf_keras/keras/applications/resnet_v2/__init__.py
keras/_tf_keras/keras/applications/vgg16/__init__.py
keras/_tf_keras/keras/applications/vgg19/__init__.py
keras/_tf_keras/keras/applications/xception/__init__.py
keras/_tf_keras/keras/backend/__init__.py
keras/_tf_keras/keras/callbacks/__init__.py
keras/_tf_keras/keras/config/__init__.py
keras/_tf_keras/keras/constraints/__init__.py
keras/_tf_keras/keras/datasets/__init__.py
keras/_tf_keras/keras/datasets/boston_housing/__init__.py
keras/_tf_keras/keras/datasets/california_housing/__init__.py
keras/_tf_keras/keras/datasets/cifar10/__init__.py
keras/_tf_keras/keras/datasets/cifar100/__init__.py
keras/_tf_keras/keras/datasets/fashion_mnist/__init__.py
keras/_tf_keras/keras/datasets/imdb/__init__.py
keras/_tf_keras/keras/datasets/mnist/__init__.py
keras/_tf_keras/keras/datasets/reuters/__init__.py
keras/_tf_keras/keras/distillation/__init__.py
keras/_tf_keras/keras/distribution/__init__.py
keras/_tf_keras/keras/dtype_policies/__init__.py
keras/_tf_keras/keras/export/__init__.py
keras_nightly-3.14.0.dev2026020104.dist-info/METADATA
keras_nightly-3.14.0.dev2026020104.dist-info/WHEEL
keras_nightly-3.14.0.dev2026020104.dist-info/top_level.txt
keras_nightly-3.14.0.dev2026020104.dist-info/RECORD
